neuralmag/__init__.py
neuralmag/backends/jax/__init__.py
neuralmag/backends/jax/code_generation.py
neuralmag/backends/jax/demag_field.py
neuralmag/backends/jax/llg_solver_jax.py
neuralmag/backends/jax/tensor_operations.py
neuralmag/backends/torch/__init__.py
neuralmag/backends/torch/code_generation.py
neuralmag/backends/torch/demag_field.py
neuralmag/backends/torch/llg_solver_torch.py
neuralmag/backends/torch/tensor_operations.py
neuralmag/common/__init__.py
neuralmag/common/code_class.py
neuralmag/common/config.py
neuralmag/common/engine.py
neuralmag/common/function.py
neuralmag/common/logging.py
neuralmag/common/mesh.py
neuralmag/common/state.py
neuralmag/field_terms/__init__.py
neuralmag/field_terms/bulk_dmi_field.py
neuralmag/field_terms/cubic_anisotropy_field.py
neuralmag/field_terms/demag_field.py
neuralmag/field_terms/exchange_field.py
neuralmag/field_terms/external_field.py
neuralmag/field_terms/field_term.py
neuralmag/field_terms/interface_dmi_field.py
neuralmag/field_terms/interlayer_exchange_field.py
neuralmag/field_terms/total_field.py
neuralmag/field_terms/uniaxial_anisotropy_field.py
neuralmag/loggers/__init__.py
neuralmag/loggers/field_logger.py
neuralmag/loggers/logger.py
neuralmag/loggers/scalar_logger.py
neuralmag/solvers/__init__.py
neuralmag/solvers/llg_solver.py
neuralmag-0.9.3.dist-info/licenses/LICENSE
neuralmag-0.9.3.dist-info/METADATA
neuralmag-0.9.3.dist-info/WHEEL
neuralmag-0.9.3.dist-info/top_level.txt
neuralmag-0.9.3.dist-info/RECORD
