Metadata-Version: 2.4
Name: neuralmag
Version: 0.9.3
Summary: NeuralMag is a micromagnetic GPU code implementing the nodal FD discretization
Author-email: Claas Abert <claas.abert@univie.ac.at>, Florian Bruckner <florian.bruckner@univie.ac.at>, Martin Lang <martin.lang@mpsd.mpg.de>, Swapneel Amit Pathak <swapneel-amit.pathak@mpsd.mpg.de>, Samuel Holt <samuel.holt@mpsd.mpg.de>, Hans Fangohr <hans.fangohr@mpsd.mpg.de>
Requires-Python: >=3.8
License-File: LICENSE
Requires-Dist: numpy
Requires-Dist: sympy
Requires-Dist: pyvista
Requires-Dist: scipy
Requires-Dist: tqdm
Provides-Extra: dev
Requires-Dist: pytest; extra == "dev"
Requires-Dist: pre-commit; extra == "dev"
Requires-Dist: nbsphinx; extra == "dev"
Requires-Dist: pydata-sphinx-theme; extra == "dev"
Requires-Dist: jupyterlab; extra == "dev"
Requires-Dist: nbval; extra == "dev"
Requires-Dist: black; extra == "dev"
Requires-Dist: isort; extra == "dev"
Provides-Extra: torch
Requires-Dist: torch; extra == "torch"
Requires-Dist: torchdiffeq; extra == "torch"
Provides-Extra: jax
Requires-Dist: jax[cuda]>=0.4.31; extra == "jax"
Requires-Dist: diffrax; extra == "jax"
Requires-Dist: optax; extra == "jax"
Dynamic: license-file
